scimorph/__init__.py
scimorph/main.py
scimorph/savefig.py
scimorph/theme_publication.py
scimorph/utils.py
scimorph/styles/publication.mplstyle
scimorph/styles/color/bright.mplstyle
scimorph/styles/color/high-contrast.mplstyle
scimorph/styles/color/high-vis.mplstyle
scimorph/styles/color/light.mplstyle
scimorph/styles/color/muted.mplstyle
scimorph/styles/color/retro.mplstyle
scimorph/styles/color/std-colors.mplstyle
scimorph/styles/color/vibrant.mplstyle
scimorph/styles/color/discrete-rainbow/discrete-rainbow-1.mplstyle
scimorph/styles/color/discrete-rainbow/discrete-rainbow-10.mplstyle
scimorph/styles/color/discrete-rainbow/discrete-rainbow-11.mplstyle
scimorph/styles/color/discrete-rainbow/discrete-rainbow-12.mplstyle
scimorph/styles/color/discrete-rainbow/discrete-rainbow-13.mplstyle
scimorph/styles/color/discrete-rainbow/discrete-rainbow-14.mplstyle
scimorph/styles/color/discrete-rainbow/discrete-rainbow-15.mplstyle
scimorph/styles/color/discrete-rainbow/discrete-rainbow-16.mplstyle
scimorph/styles/color/discrete-rainbow/discrete-rainbow-17.mplstyle
scimorph/styles/color/discrete-rainbow/discrete-rainbow-18.mplstyle
scimorph/styles/color/discrete-rainbow/discrete-rainbow-19.mplstyle
scimorph/styles/color/discrete-rainbow/discrete-rainbow-2.mplstyle
scimorph/styles/color/discrete-rainbow/discrete-rainbow-20.mplstyle
scimorph/styles/color/discrete-rainbow/discrete-rainbow-21.mplstyle
scimorph/styles/color/discrete-rainbow/discrete-rainbow-22.mplstyle
scimorph/styles/color/discrete-rainbow/discrete-rainbow-23.mplstyle
scimorph/styles/color/discrete-rainbow/discrete-rainbow-3.mplstyle
scimorph/styles/color/discrete-rainbow/discrete-rainbow-4.mplstyle
scimorph/styles/color/discrete-rainbow/discrete-rainbow-5.mplstyle
scimorph/styles/color/discrete-rainbow/discrete-rainbow-6.mplstyle
scimorph/styles/color/discrete-rainbow/discrete-rainbow-7.mplstyle
scimorph/styles/color/discrete-rainbow/discrete-rainbow-8.mplstyle
scimorph-1.0.3.dist-info/LICENSE
scimorph-1.0.3.dist-info/METADATA
scimorph-1.0.3.dist-info/WHEEL
scimorph-1.0.3.dist-info/top_level.txt
scimorph-1.0.3.dist-info/RECORD
